trump/datadef.py
trump/handling.py
trump/options.py
trump/orm.py
trump/indexing.py
trump/validity.py
trump/__init__.py
trump/reporting/objects.py
trump/reporting/__init__.py
trump/reporting/test/test_objects.py
trump/extensions/loader.py
trump/extensions/__init__.py
trump/extensions/source/tx-pydatacsv/pydatacsvext.py
trump/extensions/source/tx-pydatacsv/__init__.py
trump/extensions/source/tx-pydatadatareaderst/pydatadatareaderstext.py
trump/extensions/source/tx-pydatadatareaderst/__init__.py
trump/extensions/source/tx-psycopg2/psycopg2ext.py
trump/extensions/source/tx-psycopg2/__init__.py
trump/extensions/source/tx-bbfetch/bbfetchext.py
trump/extensions/source/tx-bbfetch/__init__.py
trump/extensions/source/tx-worldbankst/worldbankstext.py
trump/extensions/source/tx-worldbankst/__init__.py
trump/extensions/source/tx-sqlalchemy/sqlalchemyext.py
trump/extensions/source/tx-sqlalchemy/__init__.py
trump/extensions/source/tx-trump/trumpext.py
trump/extensions/source/tx-trump/__init__.py
trump/extensions/source/tx-dbapi/dbapiext.py
trump/extensions/source/tx-dbapi/__init__.py
trump/extensions/source/tx-quandl/__init__.py
trump/extensions/source/tx-quandl/quandlext.py
trump/aggregation/symbol_aggs.py
trump/aggregation/__init__.py
trump/aggregation/test/test_symbol_aggs.py
trump/test/test_orm.py
trump/test/test_indexing.py
trump/test/test_orm_exceptions.py
trump/test/test_handling.py
trump/test/testdata/fxdata4.csv
trump/test/testdata/fxdata.csv
trump/test/testdata/fxdata2.csv
trump/test/testdata/teststrdata2.csv
trump/test/testdata/testdailydata.csv
trump/test/testdata/teststrdata.csv
trump/test/testdata/emptydata.csv
trump/test/testdata/testdata.csv
trump/test/testdata/fxdata3.csv
trump/templating/bases.py
trump/templating/source_helpers.py
trump/templating/converters.py
trump/templating/__init__.py
trump/templating/munging_helpers.py
trump/templating/templates.py
trump/templating/test/test_converters.py
Trump-0.0.5.dist-info/METADATA
Trump-0.0.5.dist-info/metadata.json
Trump-0.0.5.dist-info/RECORD
Trump-0.0.5.dist-info/DESCRIPTION.rst
Trump-0.0.5.dist-info/top_level.txt
Trump-0.0.5.dist-info/pbr.json
Trump-0.0.5.dist-info/WHEEL
