Metadata-Version: 2.0
Name: Trump
Version: 0.0.5
Summary: Persistent Objectified Indexed Data
Home-page: http://Equitable.github.com/trump/
Author: Jeffrey McLarty
Author-email: jeffrey.mclarty@gmail.com
License: UNKNOWN
Download-URL: https://github.com/Equitable/trump/tarball/0.0.5
Keywords: data,timeseries,time series,indexed,objectified,trump,monotonic,RDD,relational database,pandas,SQLAlchemy
Platform: UNKNOWN
Classifier: Development Status :: 1 - Planning
Classifier: Intended Audience :: System Administrators
Classifier: License :: OSI Approved :: BSD License
Classifier: Topic :: Database
Classifier: Topic :: Office/Business
Classifier: Topic :: Scientific/Engineering
Classifier: Operating System :: OS Independent
Classifier: Programming Language :: Python :: 2.7
Requires-Dist: smuggle
Requires-Dist: pandas
Requires-Dist: SQLAlchemy
Requires-Dist: Quandl
Requires-Dist: validada
